<annotation>
	<folder>nao</folder>
	<filename>8.jpg</filename>
	<path>/home/lagrue/Documents/DEEPDART/RESSOURCES/downloads/nao/8.jpg</path>
	<source>
		<database>Unknown</database>
	</source>
	<size>
		<width>3840</width>
		<height>5760</height>
		<depth>3</depth>
	</size>
	<segmented>0</segmented>
	<object>
		<name>nao</name>
		<pose>Unspecified</pose>
		<truncated>0</truncated>
		<difficult>0</difficult>
		<bndbox>
			<xmin>338</xmin>
			<ymin>1257</ymin>
			<xmax>3493</xmax>
			<ymax>5157</ymax>
		</bndbox>
	</object>
</annotation>
